{
    "nonPerformedRunners": [
        {
            "name": "Test Runner Test Runner",
            "cafCount": 5,
            "hubName": "H1Z1R1C1P",
            "targetCount": 200
        },
        {
            "name": " Test Runner",
            "cafCount": 50,
            "hubName": "H1Z1R1C1P",
            "targetCount": 200
        },
        {
            "name": " Runner Test ",
            "cafCount": 55,
            "hubName": "H1Z1R1C1P",
            "targetCount": 200
        }
    ]
}